{
  "schemaVersion": "0.3",
  "description": "Apply mogam-admin sudoers to target EC2",
  "parameters": {
    "InstanceId": {
      "type": "String",
      "description": "EC2 instance ID"
    }
  },
  "mainSteps": [
    {
      "name": "ApplyAdminSudoers",
      "action": "aws:runCommand",
      "inputs": {
        "DocumentName": "AWS-RunShellScript",
        "InstanceIds": ["{{ InstanceId }}"],
        "Parameters": {
          "commands": [
            "echo \"$(cat /home/app/ansible/regions/us-east-1/automation/admin/admin.b64)\" | base64 -d | sudo tee /etc/sudoers.d/mogam-admin > /dev/null",
            "sudo chmod 440 /etc/sudoers.d/mogam-admin"
          ]
        }
      }
    }
  ]
}
